aiojarm/__init__.py
aiojarm/cli.py
aiojarm-0.2.2.dist-info/entry_points.txt
aiojarm-0.2.2.dist-info/LICENSE.txt
aiojarm-0.2.2.dist-info/WHEEL
aiojarm-0.2.2.dist-info/METADATA
aiojarm-0.2.2.dist-info/RECORD
