Metadata-Version: 2.1
Name: aiojarm
Version: 0.2.2
Summary: Async JARM client
Author: Manabu Niseki
Author-email: manabu.niseki@gmail.com
Requires-Python: >=3.7,<4.0
Classifier: Programming Language :: Python :: 3
Classifier: Programming Language :: Python :: 3.10
Classifier: Programming Language :: Python :: 3.7
Classifier: Programming Language :: Python :: 3.8
Classifier: Programming Language :: Python :: 3.9
Requires-Dist: aiometer (>=0.3.0,<0.4.0)
Requires-Dist: importlib-metadata (>=4.8.1,<5.0.0); python_version < "3.8"
Requires-Dist: typer (>=0.4.0,<0.5.0)
